ExampleLIS/Funciones.py
ExampleLIS/__init__.py
ExampleLIS-0.0.1.dist-info/METADATA
ExampleLIS-0.0.1.dist-info/WHEEL
ExampleLIS-0.0.1.dist-info/top_level.txt
ExampleLIS-0.0.1.dist-info/RECORD
